sphinx_bluebrain_theme/__init__.py
sphinx_bluebrain_theme/base.html
sphinx_bluebrain_theme/layout.html
sphinx_bluebrain_theme/search.html
sphinx_bluebrain_theme/theme.conf
sphinx_bluebrain_theme/version.py
sphinx_bluebrain_theme/ext/__init__.py
sphinx_bluebrain_theme/ext/details.py
sphinx_bluebrain_theme/ext/iframe.py
sphinx_bluebrain_theme/ext/tabs.py
sphinx_bluebrain_theme/partials/footer.html
sphinx_bluebrain_theme/partials/header.html
sphinx_bluebrain_theme/partials/hero.html
sphinx_bluebrain_theme/partials/language.html
sphinx_bluebrain_theme/partials/nav-item.html
sphinx_bluebrain_theme/partials/nav.html
sphinx_bluebrain_theme/partials/palette.html
sphinx_bluebrain_theme/partials/search.html
sphinx_bluebrain_theme/partials/social.html
sphinx_bluebrain_theme/partials/source.html
sphinx_bluebrain_theme/partials/tabs-item.html
sphinx_bluebrain_theme/partials/tabs.html
sphinx_bluebrain_theme/partials/toc-item.html
sphinx_bluebrain_theme/partials/toc.html
sphinx_bluebrain_theme/partials/language/ar.html
sphinx_bluebrain_theme/partials/language/ca.html
sphinx_bluebrain_theme/partials/language/cs.html
sphinx_bluebrain_theme/partials/language/da.html
sphinx_bluebrain_theme/partials/language/de.html
sphinx_bluebrain_theme/partials/language/en.html
sphinx_bluebrain_theme/partials/language/es.html
sphinx_bluebrain_theme/partials/language/fa.html
sphinx_bluebrain_theme/partials/language/fi.html
sphinx_bluebrain_theme/partials/language/fr.html
sphinx_bluebrain_theme/partials/language/gl.html
sphinx_bluebrain_theme/partials/language/gr.html
sphinx_bluebrain_theme/partials/language/he.html
sphinx_bluebrain_theme/partials/language/hi.html
sphinx_bluebrain_theme/partials/language/hr.html
sphinx_bluebrain_theme/partials/language/hu.html
sphinx_bluebrain_theme/partials/language/id.html
sphinx_bluebrain_theme/partials/language/it.html
sphinx_bluebrain_theme/partials/language/ja.html
sphinx_bluebrain_theme/partials/language/kr.html
sphinx_bluebrain_theme/partials/language/nl.html
sphinx_bluebrain_theme-0.1.0.dist-info/LICENSE.txt
sphinx_bluebrain_theme-0.1.0.dist-info/METADATA
sphinx_bluebrain_theme-0.1.0.dist-info/WHEEL
sphinx_bluebrain_theme-0.1.0.dist-info/entry_points.txt
sphinx_bluebrain_theme-0.1.0.dist-info/top_level.txt
sphinx_bluebrain_theme-0.1.0.dist-info/RECORD
